odoo/addons/account_check_printing_report_dlt103/README.rst
odoo/addons/account_check_printing_report_dlt103/__init__.py
odoo/addons/account_check_printing_report_dlt103/__manifest__.py
odoo/addons/account_check_printing_report_dlt103/data/report_paperformat.xml
odoo/addons/account_check_printing_report_dlt103/data/report_paperformat_parameter.xml
odoo/addons/account_check_printing_report_dlt103/i18n/account_check_printing_report_dlt103.pot
odoo/addons/account_check_printing_report_dlt103/i18n/pt.po
odoo/addons/account_check_printing_report_dlt103/models/__init__.py
odoo/addons/account_check_printing_report_dlt103/models/account_journal.py
odoo/addons/account_check_printing_report_dlt103/models/res_company.py
odoo/addons/account_check_printing_report_dlt103/readme/CONFIGURE.rst
odoo/addons/account_check_printing_report_dlt103/readme/CONTRIBUTORS.rst
odoo/addons/account_check_printing_report_dlt103/readme/DESCRIPTION.rst
odoo/addons/account_check_printing_report_dlt103/readme/INSTALL.rst
odoo/addons/account_check_printing_report_dlt103/readme/USAGE.rst
odoo/addons/account_check_printing_report_dlt103/report/__init__.py
odoo/addons/account_check_printing_report_dlt103/report/account_check_writing_report.xml
odoo/addons/account_check_printing_report_dlt103/report/check_print.py
odoo/addons/account_check_printing_report_dlt103/static/description/icon.png
odoo/addons/account_check_printing_report_dlt103/static/description/index.html
odoo/addons/account_check_printing_report_dlt103/views/report_check_dlt103.xml
odoo_addon_account_check_printing_report_dlt103-15.0.1.0.1.dist-info/METADATA
odoo_addon_account_check_printing_report_dlt103-15.0.1.0.1.dist-info/WHEEL
odoo_addon_account_check_printing_report_dlt103-15.0.1.0.1.dist-info/top_level.txt
odoo_addon_account_check_printing_report_dlt103-15.0.1.0.1.dist-info/RECORD
