Metadata-Version: 2.1
Name: odoo-addon-account_check_printing_report_dlt103
Version: 15.0.1.0.1
Summary: Account Check Printing Report DLT103
Home-page: https://github.com/OCA/account-payment
Author: ForgeFlow,Serpent Consulting Services Pvt. Ltd.,Odoo Community Association (OCA)
Author-email: support@odoo-community.org
License: AGPL-3
Classifier: Programming Language :: Python
Classifier: Framework :: Odoo
Classifier: Framework :: Odoo :: 15.0
Classifier: License :: OSI Approved :: GNU Affero General Public License v3
Requires-Python: >=3.8
Requires-Dist: odoo-addon-account-check-printing-report-base<15.1dev,>=15.0dev
Requires-Dist: odoo-addon-report-wkhtmltopdf-param<15.1dev,>=15.0dev
Requires-Dist: odoo<15.1dev,>=15.0a
